Metadata-Version: 2.1
Name: pytorch-basic-frame
Version: 0.0.3
Summary: A frame for training in pytorch
Home-page: https://github.com/TaoChenyue/pytorch-basic-frame
Author: TaoChenyue
Author-email: 3038816978@qq.com
License: MIT
Requires-Python: >=3.8
License-File: LICENSE
